{
  "hasDrugsFelony": false,
  "hasDrugsMisdemeanor": false,
  "hasDuiFelony": false,
  "hasDuiMisdemeanor": false,
  "hasUnclassifiedFelony": false,
  "hasUnclassifiedMisdemeanor": false,
  "hasPropertyFelony": false,
  "hasPropertyMisdemeanor": false,
  "hasSexFelony": false,
  "hasSexMisdemeanor": false,
  "hasTheftFelony": false,
  "hasTheftMisdemeanor": false,
  "hasTheftByCheckFelony": false,
  "hasTheftByCheckMisdemeanor": false,
  "hasTrafficFelony": false,
  "hasTrafficMisdemeanor": false,
  "hasViolentCrimeFelony": false,
  "hasViolentCrimeMisdemeanor": false,
  "hasWeaponsFelony": false,
  "hasWeaponsMisdemeanor": false,
  "hasRegisteredSexOffender": false,
  "hasRegisteredSexOffenderDobOnly": false,
  "hasGlobalSanctions": false,
  "hasGlobalSanctionsFuzzy": false,
  "hasEvictionRecordsMin": false,
  "hasEvictionRecordsMax": false,
  "hasEvictionFilingsMin": false,
  "hasEvictionFilingsMax": false
}
